gopher/__init__.py
gopher/annotations.py
gopher/config.py
gopher/display_data.py
gopher/enrichment.py
gopher/gopher.py
gopher/graph_search.py
gopher/normalize.py
gopher/ontologies.py
gopher/stats.py
gopher/utils.py
gopher/version.py
gopher/parsers/__init__.py
gopher/parsers/tabular.py
gopher_enrich-0.1.0.dist-info/LICENSE
gopher_enrich-0.1.0.dist-info/METADATA
gopher_enrich-0.1.0.dist-info/WHEEL
gopher_enrich-0.1.0.dist-info/entry_points.txt
gopher_enrich-0.1.0.dist-info/top_level.txt
gopher_enrich-0.1.0.dist-info/RECORD
