Metadata-Version: 2.1
Name: gopher-enrich
Version: 0.1.0
Summary: Gene ontology enrichment analysis using protein expression.
Home-page: https://github.com/TalusBio/gopher
Author: William E Fondrie
Author-email: fondriew@gmail.com
License: Apache 2.0
Project-URL: Documentation, https://TalusBio.github.io/gopher
Project-URL: Bug Tracker, https://github.com/TalusBio/gopher/issues
Project-URL: Discussion Board, https://github.com/TalusBio/gopher/discussions
Classifier: Programming Language :: Python :: 3
Classifier: License :: OSI Approved
Classifier: Operating System :: OS Independent
Classifier: Topic :: Scientific/Engineering :: Bio-Informatics
Requires-Python: >=3.6
License-File: LICENSE
Requires-Dist: numpy
Requires-Dist: pandas
Requires-Dist: scipy (>=1.7.1)
Requires-Dist: statsmodels
Requires-Dist: requests
Requires-Dist: numba
Requires-Dist: seaborn
Requires-Dist: biopython
Provides-Extra: dev
Requires-Dist: pre-commit (>=2.7.1) ; extra == 'dev'
Requires-Dist: black (>=19.10b0) ; extra == 'dev'
Provides-Extra: docs
Requires-Dist: numpydoc (>=1.0.0) ; extra == 'docs'
Requires-Dist: sphinx-argparse (>=0.2.5) ; extra == 'docs'
Requires-Dist: pydata-sphinx-theme (>=0.4.3) ; extra == 'docs'
Requires-Dist: nbsphinx (>=0.7.1) ; extra == 'docs'
Requires-Dist: ipykernel (>=5.3.0) ; extra == 'docs'
Requires-Dist: recommonmark (>=0.5.0) ; extra == 'docs'
